swerex/__init__.py
swerex/exceptions.py
swerex/py.typed
swerex/server.py
swerex/deployment/__init__.py
swerex/deployment/abstract.py
swerex/deployment/config.py
swerex/deployment/docker.py
swerex/deployment/dummy.py
swerex/deployment/fargate.py
swerex/deployment/local.py
swerex/deployment/modal.py
swerex/deployment/remote.py
swerex/deployment/hooks/__init__.py
swerex/deployment/hooks/abstract.py
swerex/deployment/hooks/status.py
swerex/runtime/__init__.py
swerex/runtime/abstract.py
swerex/runtime/config.py
swerex/runtime/dummy.py
swerex/runtime/local.py
swerex/runtime/remote.py
swerex/utils/__init__.py
swerex/utils/aws.py
swerex/utils/free_port.py
swerex/utils/log.py
swerex/utils/wait.py
0fdb5604-1.0.16.dist-info/LICENSE.txt
0fdb5604-1.0.16.dist-info/METADATA
0fdb5604-1.0.16.dist-info/WHEEL
0fdb5604-1.0.16.dist-info/entry_points.txt
0fdb5604-1.0.16.dist-info/top_level.txt
0fdb5604-1.0.16.dist-info/RECORD
